pypose/__init__.py
pypose/_version.py
pypose/basics/__init__.py
pypose/basics/ops.py
pypose/func/__init__.py
pypose/func/jac.py
pypose/function/__init__.py
pypose/function/checking.py
pypose/function/geometry.py
pypose/function/linalg.py
pypose/function/spline.py
pypose/lietensor/__init__.py
pypose/lietensor/basics.py
pypose/lietensor/convert.py
pypose/lietensor/lietensor.py
pypose/lietensor/operation.py
pypose/lietensor/utils.py
pypose/metric/__init__.py
pypose/metric/ape_rpe.py
pypose/module/__init__.py
pypose/module/dynamics.py
pypose/module/ekf.py
pypose/module/icp.py
pypose/module/imu_preintegrator.py
pypose/module/loss.py
pypose/module/lqr.py
pypose/module/mpc.py
pypose/module/pf.py
pypose/module/pnp.py
pypose/module/ukf.py
pypose/optim/__init__.py
pypose/optim/corrector.py
pypose/optim/functional.py
pypose/optim/kernel.py
pypose/optim/optimizer.py
pypose/optim/scheduler.py
pypose/optim/solver.py
pypose/optim/strategy.py
pypose/sparse/__init__.py
pypose/sparse/ops.py
pypose/testing/__init__.py
pypose/testing/comparison.py
pypose/utils/__init__.py
pypose/utils/collect_env.py
pypose/utils/stepper.py
pypose-0.7.5.data/data/docs.txt
pypose-0.7.5.data/data/runtime.txt
pypose-0.7.5.dist-info/licenses/LICENSE
pypose-0.7.5.dist-info/METADATA
pypose-0.7.5.dist-info/WHEEL
pypose-0.7.5.dist-info/top_level.txt
pypose-0.7.5.dist-info/zip-safe
pypose-0.7.5.dist-info/RECORD
