Metadata-Version: 2.4
Name: pypose
Version: 0.7.5
Summary: A library for differentiable robotics on manifolds.
Home-page: https://pypose.org
Download-URL: https://github.com/pypose/pypose
Author: Chen Wang and PyPose Team
Author-email: admin@pypose.org
License: Apache License 2.0
Project-URL: Bug Tracker, https://github.com/pypose/pypose/issues
Project-URL: Documentation, https://pypose.org/docs
Project-URL: Source Code, https://github.com/pypose/pypose
Keywords: robotics,deep learning,pytorch
Classifier: Environment :: GPU
Classifier: Environment :: Console
Classifier: Natural Language :: English
Classifier: Development Status :: 4 - Beta
Classifier: Intended Audience :: Developers
Classifier: Intended Audience :: Education
Classifier: Intended Audience :: Science/Research
Classifier: Topic :: Software Development :: Libraries
Classifier: Topic :: Scientific/Engineering :: Artificial Intelligence
Classifier: License :: OSI Approved :: Apache Software License
Classifier: Operating System :: OS Independent
Classifier: Programming Language :: Python :: 3
Classifier: Programming Language :: Python :: 3.6
Classifier: Programming Language :: Python :: 3.7
Classifier: Programming Language :: Python :: 3.8
Classifier: Programming Language :: Python :: 3.9
Classifier: Programming Language :: Python :: 3.10
Classifier: Programming Language :: Python :: 3.11
Classifier: Programming Language :: Python :: 3.12
Classifier: Programming Language :: Python :: 3.13
Classifier: Programming Language :: Python :: 3.14
Requires-Python: >=3.6
License-File: LICENSE
Requires-Dist: pytest>=7
Requires-Dist: torch==2.*
Provides-Extra: runtime
Requires-Dist: pytest>=7; extra == "runtime"
Requires-Dist: torch==2.*; extra == "runtime"
Provides-Extra: docs
Requires-Dist: sphinx==5.0.0; extra == "docs"
Requires-Dist: sphinxcontrib.katex; extra == "docs"
Requires-Dist: sphinx_rtd_theme; extra == "docs"
Requires-Dist: pypose_sphinx_theme; extra == "docs"
Provides-Extra: all
Requires-Dist: pytest>=7; extra == "all"
Requires-Dist: pypose_sphinx_theme; extra == "all"
Requires-Dist: sphinx==5.0.0; extra == "all"
Requires-Dist: torch==2.*; extra == "all"
Requires-Dist: sphinxcontrib.katex; extra == "all"
Requires-Dist: sphinx_rtd_theme; extra == "all"
Dynamic: author
Dynamic: author-email
Dynamic: classifier
Dynamic: description
Dynamic: description-content-type
Dynamic: download-url
Dynamic: home-page
Dynamic: keywords
Dynamic: license
Dynamic: license-file
Dynamic: project-url
Dynamic: provides-extra
Dynamic: requires-dist
Dynamic: requires-python
Dynamic: summary
